HelmState/Main.py
HelmState/__init__.py
HelmState/__main__.py
HelmState/Tools/ArgumentTools.py
HelmState/Tools/DumpTools.py
HelmState/Tools/GitTools.py
HelmState/Tools/StateHandler.py
HelmState/Tools/__init__.py
HelmState-1.0.22.dist-info/LICENSE
HelmState-1.0.22.dist-info/METADATA
HelmState-1.0.22.dist-info/WHEEL
HelmState-1.0.22.dist-info/entry_points.txt
HelmState-1.0.22.dist-info/top_level.txt
HelmState-1.0.22.dist-info/RECORD
