Metadata-Version: 2.1
Name: HelmState
Version: 1.0.22
Summary: Helm state tool
Home-page: https://github.com/hansehe/HelmState
Author: Hans Erik Heggem
Author-email: hans.erik.heggem@gmail.com
License: UNKNOWN
Keywords: Helm State
Platform: UNKNOWN
Classifier: Development Status :: 5 - Production/Stable
Classifier: Intended Audience :: Developers
Classifier: Topic :: Software Development :: Build Tools
Classifier: License :: OSI Approved :: MIT License
Classifier: Programming Language :: Python :: 3
Classifier: Programming Language :: Python :: 3.4
Classifier: Programming Language :: Python :: 3.5
Classifier: Programming Language :: Python :: 3.6
License-File: LICENSE
Requires-Dist: gitpython
Requires-Dist: PyYAML
Provides-Extra: dev
Requires-Dist: check-manifest ; extra == 'dev'
Provides-Extra: test
Requires-Dist: coverage ; extra == 'test'
